pymipago/__init__.py
pymipago/constants.py
pymipago/exceptions.py
pymipago/utils.py
pymipago-1.0.dist-info/DESCRIPTION.rst
pymipago-1.0.dist-info/METADATA
pymipago-1.0.dist-info/RECORD
pymipago-1.0.dist-info/WHEEL
pymipago-1.0.dist-info/metadata.json
pymipago-1.0.dist-info/top_level.txt
