Metadata-Version: 2.0
Name: pymipago
Version: 1.0
Summary: Python package to make payment requests with Basque Government payment service
Home-page: https://github.com/codesyntax/pymipago
Author: Mikel Larreategi
Author-email: mlarreategi@codesyntax.com
License: GNU General Public License v3
Keywords: pymipago
Platform: UNKNOWN
Classifier: Development Status :: 2 - Pre-Alpha
Classifier: Intended Audience :: Developers
Classifier: License :: OSI Approved :: GNU General Public License v3 (GPLv3)
Classifier: Natural Language :: English
Classifier: Programming Language :: Python :: 2
Classifier: Programming Language :: Python :: 2.7
Classifier: Programming Language :: Python :: 3
Classifier: Programming Language :: Python :: 3.4
Classifier: Programming Language :: Python :: 3.5
Classifier: Programming Language :: Python :: 3.6
Requires-Dist: requests
